unleash_client/__init__.py
unleash_client/__main__.py
unleash_client/clients.py
unleash_client/features.py
unleash_client/io.py
unleash_client/strategy.py
unleash_client/util.py
unleash_client-0.0.1.dist-info/DESCRIPTION.rst
unleash_client-0.0.1.dist-info/METADATA
unleash_client-0.0.1.dist-info/RECORD
unleash_client-0.0.1.dist-info/WHEEL
unleash_client-0.0.1.dist-info/metadata.json
unleash_client-0.0.1.dist-info/top_level.txt
