Metadata-Version: 2.0
Name: unleash-client
Version: 0.0.1
Summary: Client for the Unleash feature toggle service
Home-page: https://github.com/aes/unleash-client-python
Author: Anders Eurenius
Author-email: anders.eurenius@klarna.com
License: License :: OSI Approved :: Apache Software License
Download-URL: https://github.com/aes/unleash-client-python/archive/0.0.1.zip
Platform: UNKNOWN
Classifier: Development Status :: 3 - Alpha
Classifier: Intended Audience :: Developers
Classifier: Programming Language :: Python :: 3
Requires-Dist: requests
